client_render-0.71.data/scripts/render.ps1
render/__init__.py
render/celery.py
render/celeryconfig.py
render/logger.py
render/s3.py
render/util.py
render/watch/__init__.py
render/watch/__main__.py
render/watch/logs.py
render/watch/screen.py
render/watch/stat.py
render/watch/window.py
client_render-0.71.dist-info/LICENSE
client_render-0.71.dist-info/METADATA
client_render-0.71.dist-info/WHEEL
client_render-0.71.dist-info/top_level.txt
client_render-0.71.dist-info/RECORD
