Metadata-Version: 2.1
Name: client-render
Version: 0.71
Summary: UNKNOWN
Home-page: https://github.com/telepenin/client-render/
Author: Nikolay Telepenin
Author-email: telepenin.nikolay@gmail.com
License: MIT
Platform: UNKNOWN
Classifier: Topic :: Multimedia :: Graphics :: 3D Rendering
Classifier: Intended Audience :: Developers
Classifier: Environment :: Win32 (MS Windows)
Classifier: Natural Language :: English
Classifier: Operating System :: Microsoft :: Windows
Classifier: Programming Language :: Python
Classifier: License :: OSI Approved :: MIT License
Classifier: Development Status :: 5 - Production/Stable
Classifier: Programming Language :: Python
Classifier: Programming Language :: Python :: 3.7
Classifier: Programming Language :: Python :: 3.8
Requires-Python: >=3.7
Requires-Dist: boto3 (==1.14.6)
Requires-Dist: celery (==4.4.3)
Requires-Dist: mss (==5.1.0)
Requires-Dist: pywin32 (==228)
Requires-Dist: psutil (==5.7.0)
